{
  "$schema": "https://developer.microsoft.com/json-schemas/fabric/item/report/definition/visualContainer/2.9.0/schema.json",
  "name": "43b60ada4608ec250d6e",
  "position": {
    "x": 230.13123359580052,
    "y": 119.26509186351706,
    "z": 0,
    "height": 263.72703412073491,
    "width": 737.42782152230973
  },
  "visual": {
    "visualType": "clusteredColumnChart",
    "query": {
      "queryState": {
        "Category": {
          "projections": [
            {
              "field": {
                "Column": {
                  "Expression": {
                    "SourceRef": {
                      "Entity": "sales_table"
                    }
                  },
                  "Property": "Month"
                }
              },
              "queryRef": "sales_table.Month",
              "nativeQueryRef": "Month",
              "active": true
            }
          ]
        },
        "Y": {
          "projections": [
            {
              "field": {
                "Aggregation": {
                  "Expression": {
                    "Column": {
                      "Expression": {
                        "SourceRef": {
                          "Entity": "sales_table"
                        }
                      },
                      "Property": "Sale Amount"
                    }
                  },
                  "Function": 0
                }
              },
              "queryRef": "Sum(sales_table.Sale Amount)",
              "nativeQueryRef": "Sum of Sale Amount"
            }
          ]
        }
      },
      "sortDefinition": {
        "sort": [
          {
            "field": {
              "Aggregation": {
                "Expression": {
                  "Column": {
                    "Expression": {
                      "SourceRef": {
                        "Entity": "sales_table"
                      }
                    },
                    "Property": "Sale Amount"
                  }
                },
                "Function": 0
              }
            },
            "direction": "Descending"
          }
        ],
        "isDefaultSort": true
      }
    },
    "drillFilterOtherVisuals": true
  },
  "filterConfig": {
    "filters": [
      {
        "name": "399a72d890a968085010",
        "field": {
          "Column": {
            "Expression": {
              "SourceRef": {
                "Entity": "sales_table"
              }
            },
            "Property": "Month"
          }
        },
        "type": "Categorical"
      },
      {
        "name": "8b60231fe0078e66dc20",
        "field": {
          "Aggregation": {
            "Expression": {
              "Column": {
                "Expression": {
                  "SourceRef": {
                    "Entity": "sales_table"
                  }
                },
                "Property": "Sale Amount"
              }
            },
            "Function": 0
          }
        },
        "type": "Advanced"
      }
    ]
  }
}